{"symbol":"AAPL","companyName":"Apple, Inc.","primaryExchange":"ADANQS","calculationPrice":"close","open":296,"openTime":1637823784572,"openSource":"fiiclofa","close":288.8,"closeTime":1649333467733,"closeSource":"alfifoci","high":293.735,"highTime":1639524647607,"highSource":" pl1edc inetmu5yi raeed","low":290.62,"lowTime":1614568967777,"lowSource":"riy i5eedtm p d1naeeulc","latestPrice":296.5,"latestSource":"Close","latestTime":"April 17, 2020","latestUpdate":1611689881623,"latestVolume":55915031,"iexRealtimePrice":null,"iexRealtimeSize":null,"iexLastUpdated":null,"delayedPrice":289.382,"delayedPriceTime":1604218147887,"oddLotDelayedPrice":283.74,"oddLotDelayedPriceTime":1602831048412,"extendedPrice":287.69,"extendedChange":-0.6,"extendedChangePercent":-0.0021,"extendedPriceTime":1633635661004,"previousClose":291.25,"previousVolume":39947388,"change":-4.04,"changePercent":-0.01359,"volume":54314262,"iexMarketPercent":null,"iexVolume":null,"avgTotalVolume":62955347,"iexBidPrice":null,"iexBidSize":null,"iexAskPrice":null,"iexAskSize":null,"iexOpen":null,"iexOpenTime":null,"iexClose":49.37,"iexCloseTime":1660771863120,"marketCap":1278506493816,"peRatio":22.31,"week52High":338.27,"week52Low":178.56,"ytdChange":-0.0753,"lastTradeTime":1647720148487,"isUSMarketOpen":false}